foremastutils/__init__.py
foremastutils/formats.py
foremastutils/generator.py
foremastutils/parser.py
foremast_utils-2.0.0.dist-info/LICENSE
foremast_utils-2.0.0.dist-info/METADATA
foremast_utils-2.0.0.dist-info/WHEEL
foremast_utils-2.0.0.dist-info/top_level.txt
foremast_utils-2.0.0.dist-info/RECORD
