Metadata-Version: 2.1
Name: foremast-utils
Version: 2.0.0
Summary: A utility library for Foremast that generates names based on a common naming convention.
Home-page: https://github.com/foremast/foremast-utils
Author: Foremast
Author-email: joelvasallo+foremast@gmail.com
License: Apache License (2.0)
Download-URL: https://github.com/foremast/foremast-utils
Keywords: naming python spinnaker foremast foremast-utils
Platform: OS Independent
Classifier: Development Status :: 5 - Production/Stable
Classifier: Intended Audience :: Developers
Classifier: Programming Language :: Python :: 3.6
Classifier: Programming Language :: Python :: 3.7
Classifier: Programming Language :: Python :: 3.8
Classifier: Programming Language :: Python :: 3.9
Classifier: License :: OSI Approved :: Apache Software License
Classifier: Operating System :: OS Independent
License-File: LICENSE
